yafin/__init__.py
yafin/client.py
yafin/const.py
yafin/exceptions.py
yafin/py.typed
yafin/symbol.py
yafin/symbols.py
yafin/utils.py
yafin-0.1.1.dist-info/licenses/LICENSE
yafin-0.1.1.dist-info/METADATA
yafin-0.1.1.dist-info/WHEEL
yafin-0.1.1.dist-info/top_level.txt
yafin-0.1.1.dist-info/RECORD
