Metadata-Version: 2.4
Name: yafin
Version: 0.1.1
Summary: Unofficial Yahoo Finance API client
Author: Lukin Kratas
Project-URL: Homepage, https://github.com/lukinkratas/yahoo_finance_client
Project-URL: Repository, https://github.com/lukinkratas/yahoo_finance_client
Project-URL: Issues, https://github.com/lukinkratas/yahoo_finance_client/issues
Keywords: yahoo finance,finance,api client
Classifier: Development Status :: 3 - Alpha
Classifier: Framework :: AsyncIO
Classifier: License :: OSI Approved :: MIT License
Classifier: Operating System :: OS Independent
Classifier: Programming Language :: Python :: 3.13
Classifier: Programming Language :: Python :: 3.12
Classifier: Programming Language :: Python :: 3.11
Requires-Python: >=3.11
License-File: LICENSE
Requires-Dist: curl-cffi>=0.13.0
Requires-Dist: async-lru>=2.0.5
Dynamic: license-file
